{
    "entry": {
        "@type": "http://www.w3.org/2005/Atom", 
        "content": {
            "event": {
                "@type": "http://docs.rackspace.com/core/event", 
                "dataCenter": "DFW1", 
                "duration": "PT20M", 
                "endTime": "2013-03-16T00:00:00Z", 
                "id": "e53d007a-fc23-11e1-975c-cfa6b29bb814", 
                "product": {
                    "@type": "http://docs.rackspace.com/usage/lbaas", 
                    "avgConcurrentConnectionsSum": 1, 
                    "bandWidthOut": 1000, 
                    "bandWidthOutSsl": 1000, 
                    "hasSSLConnection": true, 
                    "publicBandWidthInSum": 1000, 
                    "publicBandWidthOutSum": 1000, 
                    "resourceType": "LOADBALANCER", 
                    "serviceCode": "CloudLoadBalancers", 
                    "version": "1"
                }, 
                "rackspaceAccountNumber": "020-123456", 
                "region": "DFW", 
                "resourceId": "4a2b42f4-6c63-11e1-815b-7fcbcf67f549", 
                "startTime": "2013-03-15T11:51:11Z", 
                "tenantId": "123456", 
                "type": "USAGE_SUMMARY", 
                "version": "2"
            }
        }, 
        "title": "CloudLoadBalancers Summary"
    }
}
